{
  "1": {},
  "2": {},
  "3": {},
  "4": {},
  "5": {},
  "6": {},
  "7": {},
  "8": {},
  "9": {
    "score": 2305,
    "score_activity_balance": 2708,
    "score_previous_day": 2678,
    "score_previous_night": 1716,
    "score_recovery_index": 2212,
    "score_resting_hr": 2547,
    "score_sleep_balance": 2075,
    "score_temperature": 2870,
    "score_hrv_balance": 2102
  },
  "10": {
    "score": 463,
    "score_activity_balance": 436,
    "score_hrv_balance": 570,
    "score_previous_day": 514,
    "score_previous_night": 400,
    "score_recovery_index": 312,
    "score_resting_hr": 515,
    "score_sleep_balance": 459,
    "score_temperature": 680
  },
  "11": {},
  "12": {}
}