{
  "1": {
    "score": 1850,
    "score_activity_balance": 2099,
    "score_hrv_balance": 1295,
    "score_previous_day": 2554,
    "score_previous_night": 1591,
    "score_recovery_index": 1934,
    "score_resting_hr": 1936,
    "score_sleep_balance": 1852,
    "score_temperature": 2747
  },
  "2": {
    "score": 796,
    "score_activity_balance": 939,
    "score_hrv_balance": 557,
    "score_previous_day": 996,
    "score_previous_night": 791,
    "score_recovery_index": 829,
    "score_resting_hr": 804,
    "score_sleep_balance": 829,
    "score_temperature": 1049
  },
  "3": {},
  "4": {},
  "5": {},
  "6": {},
  "7": {},
  "8": {},
  "9": {},
  "10": {},
  "11": {},
  "12": {}
}