[
  {
    "summary_date": "2023-05-04",
    "period_id": 0,
    "is_longest": 1,
    "timezone": 120,
    "bedtime_end": "2023-05-05T07:48:59+02:00",
    "bedtime_start": "2023-05-04T23:04:59+02:00",
    "type": "long_sleep",
    "breath_average": 13.5,
    "average_breath_variation": 4,
    "duration": 31440,
    "total": 26910,
    "awake": 4530,
    "rem": 2820,
    "deep": 6810,
    "light": 17280,
    "midpoint_time": 16530,
    "efficiency": 86,
    "restless": 5,
    "onset_latency": 1470,
    "got_up_count": 0,
    "wake_up_count": 14,
    "hr_5min": [
      0,
      0,
      0,
      0,
      0,
      54,
      55,
      57,
      59,
      61,
      62,
      0,
      0,
      0,
      62,
      58,
      63,
      70,
      0,
      0,
      66,
      62,
      61,
      63,
      62,
      61,
      65,
      0,
      68,
      63,
      61,
      59,
      72,
      75,
      65,
      65,
      68,
      64,
      72,
      76,
      66,
      0,
      0,
      58,
      53,
      55,
      53,
      56,
      56,
      57,
      52,
      55,
      51,
      55,
      54,
      52,
      54,
      55,
      50,
      52,
      50,
      50,
      51,
      51,
      48,
      49,
      51,
      51,
      54,
      56,
      50,
      55,
      57,
      0,
      51,
      50,
      49,
      52,
      53,
      54,
      57,
      56,
      55,
      52,
      51,
      54,
      54,
      56,
      62,
      60,
      59,
      54,
      54,
      55,
      55,
      57,
      59,
      60,
      60,
      59,
      58,
      51,
      54,
      58,
      52
    ],
    "hr_average": 57.33,
    "hr_lowest": 48,
    "lowest_heart_rate_time_offset": 13890,
    "hypnogram_5min": "444441211111142224211222221122223442233422222221112222222222221222222223342222111122222333322221111322244",
    "rmssd": 145,
    "rmssd_5min": [
      0,
      0,
      0,
      0,
      0,
      114,
      117,
      134,
      125,
      129,
      144,
      0,
      0,
      0,
      111,
      118,
      112,
      82,
      0,
      0,
      107,
      113,
      119,
      106,
      124,
      122,
      103,
      0,
      98,
      102,
      117,
      100,
      70,
      64,
      132,
      76,
      70,
      110,
      55,
      45,
      95,
      0,
      0,
      174,
      155,
      168,
      208,
      197,
      190,
      184,
      171,
      181,
      143,
      186,
      155,
      184,
      189,
      160,
      160,
      189,
      148,
      177,
      197,
      163,
      189,
      185,
      204,
      189,
      186,
      172,
      161,
      171,
      157,
      0,
      126,
      137,
      138,
      156,
      159,
      140,
      107,
      143,
      138,
      148,
      165,
      160,
      153,
      173,
      109,
      115,
      129,
      140,
      175,
      155,
      152,
      113,
      107,
      97,
      96,
      119,
      134,
      169,
      151,
      147,
      121
    ],
    "score": 74,
    "score_alignment": 79,
    "score_deep": 97,
    "score_disturbances": 64,
    "score_efficiency": 86,
    "score_latency": 72,
    "score_rem": 37,
    "score_total": 78,
    "temperature_deviation": 0.33,
    "temperature_trend_deviation": 0.23,
    "bedtime_start_delta": -3301,
    "bedtime_end_delta": 28139,
    "midpoint_at_delta": 13229,
    "temperature_delta": 0.33
  }
]