[
  {
    "summary_date": "2023-01-16",
    "period_id": 0,
    "is_longest": 1,
    "timezone": 330,
    "bedtime_end": "2023-01-17T10:36:32+05:30",
    "bedtime_start": "2023-01-17T01:10:32+05:30",
    "type": "long_sleep",
    "breath_average": 13.25,
    "average_breath_variation": 3.5,
    "duration": 33960,
    "total": 27480,
    "awake": 6480,
    "rem": 2970,
    "deep": 8520,
    "light": 15990,
    "midpoint_time": 16950,
    "efficiency": 81,
    "restless": 5,
    "onset_latency": 960,
    "got_up_count": 0,
    "wake_up_count": 15,
    "hr_5min": [
      0,
      75,
      67,
      60,
      0,
      0,
      0,
      64,
      65,
      64,
      65,
      61,
      62,
      69,
      59,
      65,
      63,
      64,
      66,
      67,
      66,
      62,
      72,
      75,
      69,
      70,
      64,
      62,
      64,
      67,
      68,
      66,
      68,
      69,
      62,
      65,
      68,
      70,
      75,
      68,
      68,
      63,
      63,
      60,
      59,
      59,
      61,
      60,
      62,
      63,
      63,
      68,
      72,
      71,
      61,
      65,
      64,
      60,
      56,
      57,
      60,
      62,
      61,
      62,
      62,
      61,
      62,
      63,
      63,
      63,
      63,
      61,
      62,
      57,
      58,
      59,
      59,
      60,
      61,
      61,
      62,
      62,
      63,
      66,
      69,
      69,
      57,
      60,
      60,
      62,
      57,
      58,
      61,
      56,
      60,
      55,
      56,
      57,
      62,
      64,
      67,
      62,
      59,
      59,
      66,
      65,
      65,
      64,
      69,
      0,
      0,
      0,
      0,
      0
    ],
    "hr_average": 63.362,
    "hr_lowest": 55,
    "lowest_heart_rate_time_offset": 17730,
    "hypnogram_5min": "444222141112111211111422222211111122244322222222112334322222111112112222222222121122332222222222223333223322444444",
    "rmssd": 103,
    "rmssd_5min": [
      0,
      74,
      110,
      139,
      0,
      0,
      0,
      40,
      51,
      78,
      64,
      81,
      94,
      66,
      109,
      67,
      69,
      77,
      84,
      95,
      94,
      87,
      64,
      72,
      84,
      68,
      100,
      108,
      123,
      103,
      88,
      105,
      104,
      90,
      115,
      99,
      65,
      72,
      38,
      67,
      65,
      91,
      102,
      124,
      118,
      128,
      126,
      115,
      98,
      79,
      105,
      77,
      53,
      66,
      121,
      78,
      67,
      131,
      165,
      160,
      113,
      110,
      120,
      94,
      108,
      122,
      102,
      90,
      94,
      108,
      112,
      117,
      117,
      160,
      136,
      130,
      111,
      145,
      97,
      99,
      97,
      113,
      109,
      86,
      71,
      51,
      125,
      117,
      127,
      100,
      159,
      157,
      148,
      147,
      112,
      160,
      145,
      159,
      115,
      92,
      56,
      100,
      113,
      117,
      64,
      79,
      97,
      105,
      85,
      0,
      0,
      0,
      0,
      0
    ],
    "score": 71,
    "score_alignment": 20,
    "score_deep": 99,
    "score_disturbances": 63,
    "score_efficiency": 74,
    "score_latency": 97,
    "score_rem": 40,
    "score_total": 80,
    "temperature_deviation": 0.17,
    "temperature_trend_deviation": 0.12,
    "bedtime_start_delta": 4232,
    "bedtime_end_delta": 38192,
    "midpoint_at_delta": 21182,
    "temperature_delta": 0.17
  }
]