[
  {
    "summary_date": "2023-02-06",
    "period_id": 0,
    "is_longest": 1,
    "timezone": 60,
    "bedtime_end": "2023-02-07T07:55:33+01:00",
    "bedtime_start": "2023-02-06T21:54:33+01:00",
    "type": "long_sleep",
    "breath_average": 13,
    "average_breath_variation": 3.625,
    "duration": 36060,
    "total": 32700,
    "awake": 3360,
    "rem": 5730,
    "deep": 10170,
    "light": 16800,
    "midpoint_time": 18150,
    "efficiency": 91,
    "restless": 4,
    "onset_latency": 960,
    "got_up_count": 0,
    "wake_up_count": 14,
    "hr_5min": [
      0,
      56,
      0,
      0,
      0,
      0,
      0,
      56,
      56,
      55,
      58,
      58,
      60,
      0,
      0,
      55,
      58,
      67,
      0,
      53,
      56,
      0,
      55,
      55,
      58,
      60,
      57,
      54,
      55,
      0,
      60,
      66,
      59,
      58,
      59,
      62,
      62,
      60,
      60,
      60,
      55,
      57,
      58,
      59,
      58,
      58,
      58,
      52,
      50,
      51,
      52,
      61,
      63,
      58,
      57,
      56,
      55,
      58,
      58,
      59,
      60,
      61,
      56,
      52,
      51,
      54,
      54,
      58,
      59,
      59,
      59,
      62,
      59,
      60,
      54,
      55,
      56,
      0,
      51,
      0,
      0,
      0,
      0,
      0,
      58,
      57,
      52,
      59,
      59,
      57,
      58,
      54,
      53,
      53,
      53,
      49,
      51,
      52,
      52,
      52,
      57,
      60,
      63,
      67,
      0,
      0,
      56,
      61,
      63,
      60,
      61,
      61,
      57,
      56,
      56,
      57,
      56,
      59,
      0,
      0,
      0
    ],
    "hr_average": 57.172,
    "hr_lowest": 49,
    "lowest_heart_rate_time_offset": 14730,
    "hypnogram_5min": "4443112422111112221211221112211132222111121111122213332221111112222222222222214222122223333222222222333333333333322221444",
    "rmssd": 148,
    "rmssd_5min": [
      0,
      116,
      0,
      0,
      0,
      0,
      0,
      154,
      116,
      146,
      154,
      158,
      147,
      0,
      0,
      163,
      152,
      78,
      0,
      196,
      181,
      0,
      158,
      198,
      149,
      114,
      153,
      174,
      190,
      0,
      111,
      71,
      134,
      147,
      137,
      124,
      122,
      137,
      132,
      131,
      153,
      156,
      138,
      137,
      148,
      141,
      146,
      172,
      163,
      182,
      188,
      113,
      99,
      133,
      148,
      156,
      170,
      143,
      142,
      120,
      119,
      107,
      142,
      196,
      200,
      164,
      167,
      150,
      117,
      122,
      140,
      98,
      140,
      131,
      165,
      184,
      189,
      0,
      213,
      0,
      0,
      0,
      0,
      0,
      154,
      139,
      180,
      125,
      127,
      153,
      131,
      143,
      159,
      150,
      197,
      167,
      224,
      241,
      198,
      196,
      143,
      112,
      80,
      58,
      0,
      0,
      176,
      139,
      126,
      152,
      145,
      136,
      176,
      170,
      152,
      147,
      156,
      139,
      0,
      0,
      0
    ],
    "score": 92,
    "score_alignment": 100,
    "score_deep": 100,
    "score_disturbances": 69,
    "score_efficiency": 96,
    "score_latency": 97,
    "score_rem": 78,
    "score_total": 99,
    "temperature_deviation": -0.02,
    "temperature_trend_deviation": 0.15,
    "bedtime_start_delta": -7527,
    "bedtime_end_delta": 28533,
    "midpoint_at_delta": 10623,
    "temperature_delta": -0.02
  }
]