[
  {
    "artist": {
      "mbid": "1d8c336b-5f41-412a-a921-0d3d5ecee651",
      "#text": "Camille"
    },
    "streamable": "0",
    "image": [
      {
        "size": "small",
        "#text": "https://lastfm.freetls.fastly.net/i/u/34s/5a6368348d88b92c4fe17fddabf3d1e8.jpg"
      },
      {
        "size": "medium",
        "#text": "https://lastfm.freetls.fastly.net/i/u/64s/5a6368348d88b92c4fe17fddabf3d1e8.jpg"
      },
      {
        "size": "large",
        "#text": "https://lastfm.freetls.fastly.net/i/u/174s/5a6368348d88b92c4fe17fddabf3d1e8.jpg"
      },
      {
        "size": "extralarge",
        "#text": "https://lastfm.freetls.fastly.net/i/u/300x300/5a6368348d88b92c4fe17fddabf3d1e8.jpg"
      }
    ],
    "mbid": "7ece455d-792a-33fa-a582-f169097a36ae",
    "album": {
      "mbid": "",
      "#text": "Ratatouille (Original Motion Picture Soundtrack)"
    },
    "name": "Le festin",
    "url": "https://www.last.fm/music/Camille/_/Le+festin",
    "date": {
      "uts": "1623356228",
      "#text": "10 Jun 2021, 20:17"
    }
  },
  {
    "artist": {
      "mbid": "1d8c336b-5f41-412a-a921-0d3d5ecee651",
      "#text": "Camille"
    },
    "streamable": "0",
    "image": [
      {
        "size": "small",
        "#text": "https://lastfm.freetls.fastly.net/i/u/34s/5a6368348d88b92c4fe17fddabf3d1e8.jpg"
      },
      {
        "size": "medium",
        "#text": "https://lastfm.freetls.fastly.net/i/u/64s/5a6368348d88b92c4fe17fddabf3d1e8.jpg"
      },
      {
        "size": "large",
        "#text": "https://lastfm.freetls.fastly.net/i/u/174s/5a6368348d88b92c4fe17fddabf3d1e8.jpg"
      },
      {
        "size": "extralarge",
        "#text": "https://lastfm.freetls.fastly.net/i/u/300x300/5a6368348d88b92c4fe17fddabf3d1e8.jpg"
      }
    ],
    "mbid": "7ece455d-792a-33fa-a582-f169097a36ae",
    "album": {
      "mbid": "",
      "#text": "Ratatouille (Original Motion Picture Soundtrack)"
    },
    "name": "Le festin",
    "url": "https://www.last.fm/music/Camille/_/Le+festin",
    "date": {
      "uts": "1623356070",
      "#text": "10 Jun 2021, 20:14"
    }
  }
]