[
  {
    "id": "healthkit-7BDC1CEA-A485-4981-B59C-814A30FB1158",
    "name": "Walking",
    "description": "",
    "startTimeMillis": "1692343061899",
    "endTimeMillis": "1692344238356",
    "modifiedTimeMillis": "1707606491886",
    "application": {
      "packageName": "com.apple.workout",
      "version": "",
      "detailsUrl": ""
    },
    "activityType": 93,
    "startTime": "2023-08-18T07:17:41.899Z",
    "endTime": "2023-08-18T07:37:18.356Z"
  },
  {
    "id": "healthkit-487FBC65-B304-4C38-8338-0280E4065EB3",
    "name": "Walking",
    "description": "",
    "startTimeMillis": "1692350258567",
    "endTimeMillis": "1692351358355",
    "modifiedTimeMillis": "1707606494930",
    "application": {
      "packageName": "com.apple.workout",
      "version": "",
      "detailsUrl": ""
    },
    "activityType": 93,
    "startTime": "2023-08-18T09:17:38.567Z",
    "endTime": "2023-08-18T09:35:58.355Z"
  }
]