{
  "2022-12-18": {
    "total": 24180,
    "rem": 3180,
    "awake": 2160,
    "deep": 8640,
    "duration": 26340,
    "efficiency": 92,
    "light": 12360,
    "score": 71
  },
  "2022-12-19": {
    "total": 28290,
    "rem": 3240,
    "awake": 7410,
    "deep": 7710,
    "duration": 35700,
    "efficiency": 79,
    "light": 17340,
    "score": 78
  },
  "2022-12-20": {
    "total": 21480,
    "rem": 1620,
    "awake": 3540,
    "deep": 8340,
    "duration": 25020,
    "efficiency": 86,
    "light": 11520,
    "score": 66
  },
  "2022-12-21": {},
  "2022-12-22": {},
  "2022-12-23": {},
  "2022-12-24": {}
}