[
  {
    "grand_total": {
      "hours": 0,
      "minutes": 31,
      "total_seconds": 1897.744,
      "digital": "0:31",
      "decimal": "0.52",
      "text": "31 mins",
      "ai_additions": 0,
      "ai_deletions": 0,
      "human_additions": 977,
      "human_deletions": 211
    },
    "range": {
      "start": "2026-01-04T23:00:00Z",
      "end": "2026-01-05T22:59:59Z",
      "date": "2026-01-05",
      "text": "Mon Jan 5th 2026",
      "timezone": "Europe/Amsterdam"
    },
    "projects": [
      {
        "name": "airweave",
        "total_seconds": 1897.744,
        "ai_additions": 0,
        "ai_deletions": 0,
        "human_additions": 977,
        "human_deletions": 211,
        "color": null,
        "digital": "0:31:37",
        "decimal": "0.52",
        "text": "31 mins",
        "hours": 0,
        "minutes": 31,
        "seconds": 37,
        "percent": 100
      }
    ],
    "languages": [
      {
        "name": "TypeScript",
        "total_seconds": 1889.363,
        "digital": "0:31:29",
        "decimal": "0.52",
        "text": "31 mins",
        "hours": 0,
        "minutes": 31,
        "seconds": 29,
        "percent": 99.56
      },
      {
        "name": "CSS",
        "total_seconds": 8.381,
        "digital": "0:00:08",
        "decimal": "0.00",
        "text": "8 secs",
        "hours": 0,
        "minutes": 0,
        "seconds": 8,
        "percent": 0.44
      }
    ],
    "dependencies": [
      {
        "name": "utils",
        "total_seconds": 1486.895,
        "digital": "0:24:46",
        "decimal": "0.40",
        "text": "24 mins",
        "hours": 0,
        "minutes": 24,
        "seconds": 46,
        "percent": 11.78
      },
      {
        "name": "lucide-react",
        "total_seconds": 1376.272,
        "digital": "0:22:56",
        "decimal": "0.37",
        "text": "22 mins",
        "hours": 0,
        "minutes": 22,
        "seconds": 56,
        "percent": 10.9
      },
      {
        "name": "button",
        "total_seconds": 1359.395,
        "digital": "0:22:39",
        "decimal": "0.37",
        "text": "22 mins",
        "hours": 0,
        "minutes": 22,
        "seconds": 39,
        "percent": 10.77
      },
      {
        "name": "empty-state",
        "total_seconds": 893.848,
        "digital": "0:14:53",
        "decimal": "0.23",
        "text": "14 mins",
        "hours": 0,
        "minutes": 14,
        "seconds": 53,
        "percent": 7.08
      },
      {
        "name": "react",
        "total_seconds": 749.668,
        "digital": "0:12:29",
        "decimal": "0.20",
        "text": "12 mins",
        "hours": 0,
        "minutes": 12,
        "seconds": 29,
        "percent": 5.94
      },
      {
        "name": "tooltip",
        "total_seconds": 390.359,
        "digital": "0:06:30",
        "decimal": "0.10",
        "text": "6 mins",
        "hours": 0,
        "minutes": 6,
        "seconds": 30,
        "percent": 3.09
      },
      {
        "name": "auth-provider",
        "total_seconds": 386.164,
        "digital": "0:06:26",
        "decimal": "0.10",
        "text": "6 mins",
        "hours": 0,
        "minutes": 6,
        "seconds": 26,
        "percent": 3.06
      },
      {
        "name": "query-keys",
        "total_seconds": 379.412,
        "digital": "0:06:19",
        "decimal": "0.10",
        "text": "6 mins",
        "hours": 0,
        "minutes": 6,
        "seconds": 19,
        "percent": 3.01
      },
      {
        "name": "react-query",
        "total_seconds": 379.412,
        "digital": "0:06:19",
        "decimal": "0.10",
        "text": "6 mins",
        "hours": 0,
        "minutes": 6,
        "seconds": 19,
        "percent": 3.01
      },
      {
        "name": "react-router",
        "total_seconds": 370.71,
        "digital": "0:06:10",
        "decimal": "0.10",
        "text": "6 mins",
        "hours": 0,
        "minutes": 6,
        "seconds": 10,
        "percent": 2.94
      },
      {
        "name": "sonner",
        "total_seconds": 370.534,
        "digital": "0:06:10",
        "decimal": "0.10",
        "text": "6 mins",
        "hours": 0,
        "minutes": 6,
        "seconds": 10,
        "percent": 2.94
      },
      {
        "name": "api",
        "total_seconds": 367.893,
        "digital": "0:06:07",
        "decimal": "0.10",
        "text": "6 mins",
        "hours": 0,
        "minutes": 6,
        "seconds": 7,
        "percent": 2.91
      },
      {
        "name": "input",
        "total_seconds": 358.523,
        "digital": "0:05:58",
        "decimal": "0.08",
        "text": "5 mins",
        "hours": 0,
        "minutes": 5,
        "seconds": 58,
        "percent": 2.84
      },
      {
        "name": "create-collection-store",
        "total_seconds": 352.079,
        "digital": "0:05:52",
        "decimal": "0.08",
        "text": "5 mins",
        "hours": 0,
        "minutes": 5,
        "seconds": 52,
        "percent": 2.79
      },
      {
        "name": "org-context",
        "total_seconds": 351.411,
        "digital": "0:05:51",
        "decimal": "0.08",
        "text": "5 mins",
        "hours": 0,
        "minutes": 5,
        "seconds": 51,
        "percent": 2.78
      },
      {
        "name": "alert-dialog",
        "total_seconds": 344.659,
        "digital": "0:05:44",
        "decimal": "0.08",
        "text": "5 mins",
        "hours": 0,
        "minutes": 5,
        "seconds": 44,
        "percent": 2.73
      },
      {
        "name": "collections",
        "total_seconds": 344.659,
        "digital": "0:05:44",
        "decimal": "0.08",
        "text": "5 mins",
        "hours": 0,
        "minutes": 5,
        "seconds": 44,
        "percent": 2.73
      },
      {
        "name": "error-state",
        "total_seconds": 344.659,
        "digital": "0:05:44",
        "decimal": "0.08",
        "text": "5 mins",
        "hours": 0,
        "minutes": 5,
        "seconds": 44,
        "percent": 2.73
      },
      {
        "name": "search",
        "total_seconds": 344.659,
        "digital": "0:05:44",
        "decimal": "0.08",
        "text": "5 mins",
        "hours": 0,
        "minutes": 5,
        "seconds": 44,
        "percent": 2.73
      },
      {
        "name": "loading-state",
        "total_seconds": 344.659,
        "digital": "0:05:44",
        "decimal": "0.08",
        "text": "5 mins",
        "hours": 0,
        "minutes": 5,
        "seconds": 44,
        "percent": 2.73
      },
      {
        "name": "page-header",
        "total_seconds": 344.659,
        "digital": "0:05:44",
        "decimal": "0.08",
        "text": "5 mins",
        "hours": 0,
        "minutes": 5,
        "seconds": 44,
        "percent": 2.73
      },
      {
        "name": "right-sidebar",
        "total_seconds": 344.659,
        "digital": "0:05:44",
        "decimal": "0.08",
        "text": "5 mins",
        "hours": 0,
        "minutes": 5,
        "seconds": 44,
        "percent": 2.73
      },
      {
        "name": "types",
        "total_seconds": 90.014,
        "digital": "0:01:30",
        "decimal": "0.02",
        "text": "1 min",
        "hours": 0,
        "minutes": 1,
        "seconds": 30,
        "percent": 0.71
      },
      {
        "name": "use-docs-content",
        "total_seconds": 48.392,
        "digital": "0:00:48",
        "decimal": "0.00",
        "text": "48 secs",
        "hours": 0,
        "minutes": 0,
        "seconds": 48,
        "percent": 0.38
      },
      {
        "name": "entity-result-card",
        "total_seconds": 47.472,
        "digital": "0:00:47",
        "decimal": "0.00",
        "text": "47 secs",
        "hours": 0,
        "minutes": 0,
        "seconds": 47,
        "percent": 0.38
      },
      {
        "name": "search-trace",
        "total_seconds": 47.472,
        "digital": "0:00:47",
        "decimal": "0.00",
        "text": "47 secs",
        "hours": 0,
        "minutes": 0,
        "seconds": 47,
        "percent": 0.38
      },
      {
        "name": "use-local-storage-state",
        "total_seconds": 47.472,
        "digital": "0:00:47",
        "decimal": "0.00",
        "text": "47 secs",
        "hours": 0,
        "minutes": 0,
        "seconds": 47,
        "percent": 0.38
      },
      {
        "name": "markdown",
        "total_seconds": 40.85,
        "digital": "0:00:40",
        "decimal": "0.00",
        "text": "40 secs",
        "hours": 0,
        "minutes": 0,
        "seconds": 40,
        "percent": 0.32
      },
      {
        "name": "use-auto-scroll",
        "total_seconds": 30.621,
        "digital": "0:00:30",
        "decimal": "0.00",
        "text": "30 secs",
        "hours": 0,
        "minutes": 0,
        "seconds": 30,
        "percent": 0.24
      },
      {
        "name": "use-is-dark",
        "total_seconds": 25.875,
        "digital": "0:00:25",
        "decimal": "0.00",
        "text": "25 secs",
        "hours": 0,
        "minutes": 0,
        "seconds": 25,
        "percent": 0.2
      },
      {
        "name": "organizations",
        "total_seconds": 18.631,
        "digital": "0:00:18",
        "decimal": "0.00",
        "text": "18 secs",
        "hours": 0,
        "minutes": 0,
        "seconds": 18,
        "percent": 0.15
      },
      {
        "name": "org-utils",
        "total_seconds": 18.631,
        "digital": "0:00:18",
        "decimal": "0.00",
        "text": "18 secs",
        "hours": 0,
        "minutes": 0,
        "seconds": 18,
        "percent": 0.15
      },
      {
        "name": "user-account-dropdown",
        "total_seconds": 17.173,
        "digital": "0:00:17",
        "decimal": "0.00",
        "text": "17 secs",
        "hours": 0,
        "minutes": 0,
        "seconds": 17,
        "percent": 0.14
      },
      {
        "name": "helpers",
        "total_seconds": 16.122,
        "digital": "0:00:16",
        "decimal": "0.00",
        "text": "16 secs",
        "hours": 0,
        "minutes": 0,
        "seconds": 16,
        "percent": 0.13
      },
      {
        "name": "dialog",
        "total_seconds": 16.122,
        "digital": "0:00:16",
        "decimal": "0.00",
        "text": "16 secs",
        "hours": 0,
        "minutes": 0,
        "seconds": 16,
        "percent": 0.13
      },
      {
        "name": "sidebar",
        "total_seconds": 16.094,
        "digital": "0:00:16",
        "decimal": "0.00",
        "text": "16 secs",
        "hours": 0,
        "minutes": 0,
        "seconds": 16,
        "percent": 0.13
      },
      {
        "name": "react-form",
        "total_seconds": 13.864,
        "digital": "0:00:13",
        "decimal": "0.00",
        "text": "13 secs",
        "hours": 0,
        "minutes": 0,
        "seconds": 13,
        "percent": 0.11
      },
      {
        "name": "search-box",
        "total_seconds": 11.095,
        "digital": "0:00:11",
        "decimal": "0.00",
        "text": "11 secs",
        "hours": 0,
        "minutes": 0,
        "seconds": 11,
        "percent": 0.09
      },
      {
        "name": "search-response",
        "total_seconds": 11.095,
        "digital": "0:00:11",
        "decimal": "0.00",
        "text": "11 secs",
        "hours": 0,
        "minutes": 0,
        "seconds": 11,
        "percent": 0.09
      },
      {
        "name": "api-form",
        "total_seconds": 10.543,
        "digital": "0:00:10",
        "decimal": "0.00",
        "text": "10 secs",
        "hours": 0,
        "minutes": 0,
        "seconds": 10,
        "percent": 0.08
      },
      {
        "name": "use-keyboard-shortcut",
        "total_seconds": 10.219,
        "digital": "0:00:10",
        "decimal": "0.00",
        "text": "10 secs",
        "hours": 0,
        "minutes": 0,
        "seconds": 10,
        "percent": 0.08
      },
      {
        "name": "use-before-unload",
        "total_seconds": 9.753,
        "digital": "0:00:09",
        "decimal": "0.00",
        "text": "9 secs",
        "hours": 0,
        "minutes": 0,
        "seconds": 9,
        "percent": 0.08
      },
      {
        "name": "steps",
        "total_seconds": 9.753,
        "digital": "0:00:09",
        "decimal": "0.00",
        "text": "9 secs",
        "hours": 0,
        "minutes": 0,
        "seconds": 9,
        "percent": 0.08
      },
      {
        "name": "auth",
        "total_seconds": 9.753,
        "digital": "0:00:09",
        "decimal": "0.00",
        "text": "9 secs",
        "hours": 0,
        "minutes": 0,
        "seconds": 9,
        "percent": 0.08
      },
      {
        "name": "onboarding",
        "total_seconds": 9.753,
        "digital": "0:00:09",
        "decimal": "0.00",
        "text": "9 secs",
        "hours": 0,
        "minutes": 0,
        "seconds": 9,
        "percent": 0.08
      },
      {
        "name": "theme",
        "total_seconds": 8.674,
        "digital": "0:00:08",
        "decimal": "0.00",
        "text": "8 secs",
        "hours": 0,
        "minutes": 0,
        "seconds": 8,
        "percent": 0.07
      },
      {
        "name": "avatar",
        "total_seconds": 8.674,
        "digital": "0:00:08",
        "decimal": "0.00",
        "text": "8 secs",
        "hours": 0,
        "minutes": 0,
        "seconds": 8,
        "percent": 0.07
      },
      {
        "name": "dropdown-menu",
        "total_seconds": 8.674,
        "digital": "0:00:08",
        "decimal": "0.00",
        "text": "8 secs",
        "hours": 0,
        "minutes": 0,
        "seconds": 8,
        "percent": 0.07
      },
      {
        "name": "ui-settings",
        "total_seconds": 8.674,
        "digital": "0:00:08",
        "decimal": "0.00",
        "text": "8 secs",
        "hours": 0,
        "minutes": 0,
        "seconds": 8,
        "percent": 0.07
      },
      {
        "name": "navigation",
        "total_seconds": 7.42,
        "digital": "0:00:07",
        "decimal": "0.00",
        "text": "7 secs",
        "hours": 0,
        "minutes": 0,
        "seconds": 7,
        "percent": 0.06
      },
      {
        "name": "client",
        "total_seconds": 5.039,
        "digital": "0:00:05",
        "decimal": "0.00",
        "text": "5 secs",
        "hours": 0,
        "minutes": 0,
        "seconds": 5,
        "percent": 0.04
      },
      {
        "name": "delete-confirmation-dialog",
        "total_seconds": 2.258,
        "digital": "0:00:02",
        "decimal": "0.00",
        "text": "2 secs",
        "hours": 0,
        "minutes": 0,
        "seconds": 2,
        "percent": 0.02
      },
      {
        "name": "anand@chowdhary",
        "total_seconds": 1.973,
        "digital": "0:00:01",
        "decimal": "0.00",
        "text": "1 sec",
        "hours": 0,
        "minutes": 0,
        "seconds": 1,
        "percent": 0.02
      },
      {
        "name": "jXyLRWR9lg0kZQvVjpJ2YmiSYn1UtUSw",
        "total_seconds": 1.973,
        "digital": "0:00:01",
        "decimal": "0.00",
        "text": "1 sec",
        "hours": 0,
        "minutes": 0,
        "seconds": 1,
        "percent": 0.02
      },
      {
        "name": "Anand Chowdhary",
        "total_seconds": 1.973,
        "digital": "0:00:01",
        "decimal": "0.00",
        "text": "1 sec",
        "hours": 0,
        "minutes": 0,
        "seconds": 1,
        "percent": 0.02
      },
      {
        "name": "airweave.us.auth0",
        "total_seconds": 1.973,
        "digital": "0:00:01",
        "decimal": "0.00",
        "text": "1 sec",
        "hours": 0,
        "minutes": 0,
        "seconds": 1,
        "percent": 0.02
      },
      {
        "name": "false",
        "total_seconds": 1.973,
        "digital": "0:00:01",
        "decimal": "0.00",
        "text": "1 sec",
        "hours": 0,
        "minutes": 0,
        "seconds": 1,
        "percent": 0.02
      },
      {
        "name": "json-filter-editor",
        "total_seconds": 0.466,
        "digital": "0:00:00",
        "decimal": "0.00",
        "text": "0 secs",
        "hours": 0,
        "minutes": 0,
        "seconds": 0,
        "percent": 0
      },
      {
        "name": "recency-bias-slider",
        "total_seconds": 0.466,
        "digital": "0:00:00",
        "decimal": "0.00",
        "text": "0 secs",
        "hours": 0,
        "minutes": 0,
        "seconds": 0,
        "percent": 0
      },
      {
        "name": "api-integration-modal",
        "total_seconds": 0.466,
        "digital": "0:00:00",
        "decimal": "0.00",
        "text": "0 secs",
        "hours": 0,
        "minutes": 0,
        "seconds": 0,
        "percent": 0
      },
      {
        "name": "search-box-toggle",
        "total_seconds": 0.466,
        "digital": "0:00:00",
        "decimal": "0.00",
        "text": "0 secs",
        "hours": 0,
        "minutes": 0,
        "seconds": 0,
        "percent": 0
      }
    ],
    "machines": [
      {
        "name": "Anands-MacBook-Pro.local",
        "total_seconds": 1897.744,
        "machine_name_id": "a617626d-a441-4808-bcf9-c082444ddda5",
        "digital": "0:31:37",
        "decimal": "0.52",
        "text": "31 mins",
        "hours": 0,
        "minutes": 31,
        "seconds": 37,
        "percent": 100
      }
    ],
    "editors": [
      {
        "name": "Cursor",
        "total_seconds": 1897.744,
        "digital": "0:31:37",
        "decimal": "0.52",
        "text": "31 mins",
        "hours": 0,
        "minutes": 31,
        "seconds": 37,
        "percent": 100
      }
    ],
    "operating_systems": [
      {
        "name": "Mac",
        "total_seconds": 1897.744,
        "digital": "0:31:37",
        "decimal": "0.52",
        "text": "31 mins",
        "hours": 0,
        "minutes": 31,
        "seconds": 37,
        "percent": 100
      }
    ],
    "categories": [
      {
        "name": "Coding",
        "total_seconds": 1897.744,
        "digital": "0:31:37",
        "decimal": "0.52",
        "text": "31 mins",
        "hours": 0,
        "minutes": 31,
        "seconds": 37,
        "percent": 100
      }
    ]
  }
]