[
  {
    "summary_date": "2023-11-02",
    "period_id": 1,
    "is_longest": 1,
    "timezone": 60,
    "bedtime_end": "2023-11-03T07:51:59+01:00",
    "bedtime_start": "2023-11-03T00:58:59+01:00",
    "type": "long_sleep",
    "breath_average": 13.125,
    "average_breath_variation": 3.5,
    "duration": 24780,
    "total": 22710,
    "awake": 2070,
    "rem": 1530,
    "deep": 11340,
    "light": 9840,
    "midpoint_time": 12150,
    "efficiency": 92,
    "restless": 5,
    "onset_latency": 210,
    "got_up_count": 0,
    "wake_up_count": 11,
    "hr_5min": [
      0,
      53,
      55,
      54,
      56,
      54,
      55,
      58,
      59,
      59,
      59,
      61,
      60,
      58,
      59,
      59,
      61,
      54,
      54,
      55,
      58,
      60,
      55,
      56,
      58,
      59,
      61,
      52,
      51,
      56,
      59,
      58,
      54,
      54,
      53,
      52,
      56,
      55,
      54,
      54,
      54,
      56,
      58,
      58,
      57,
      61,
      0,
      61,
      60,
      50,
      52,
      56,
      52,
      55,
      56,
      55,
      51,
      54,
      55,
      55,
      52,
      52,
      52,
      60,
      59,
      58,
      51,
      55,
      56,
      56,
      53,
      54,
      54,
      55,
      55,
      55,
      48,
      55,
      54,
      60,
      59,
      52,
      0
    ],
    "hr_average": 55.737,
    "hr_lowest": 48,
    "lowest_heart_rate_time_offset": 14730,
    "hypnogram_5min": "42111211111111222211111111122231222211222111113322112214211122333222112211122223244",
    "rmssd": 148,
    "rmssd_5min": [
      0,
      165,
      162,
      144,
      157,
      155,
      149,
      141,
      142,
      144,
      138,
      129,
      142,
      155,
      141,
      142,
      137,
      145,
      167,
      162,
      132,
      121,
      169,
      159,
      132,
      123,
      110,
      155,
      166,
      163,
      118,
      139,
      160,
      162,
      162,
      171,
      150,
      167,
      149,
      149,
      173,
      145,
      149,
      141,
      133,
      116,
      0,
      112,
      120,
      178,
      184,
      150,
      150,
      123,
      125,
      145,
      188,
      177,
      172,
      176,
      181,
      168,
      167,
      109,
      104,
      115,
      164,
      137,
      130,
      123,
      150,
      142,
      127,
      110,
      123,
      122,
      163,
      172,
      174,
      97,
      84,
      172,
      0
    ],
    "score": 66,
    "score_alignment": 59,
    "score_deep": 100,
    "score_disturbances": 68,
    "score_efficiency": 97,
    "score_latency": 70,
    "score_rem": 20,
    "score_total": 62,
    "temperature_deviation": -0.16,
    "temperature_trend_deviation": -0.16,
    "bedtime_start_delta": 3539,
    "bedtime_end_delta": 28319,
    "midpoint_at_delta": 15689,
    "temperature_delta": -0.16
  }
]