[
  {
    "Rank": 1,
    "Time Spent (seconds)": 7535,
    "Number of People": 1,
    "Category": "Utilities"
  },
  {
    "Rank": 2,
    "Time Spent (seconds)": 6309,
    "Number of People": 1,
    "Category": "Communication & Scheduling"
  },
  {
    "Rank": 3,
    "Time Spent (seconds)": 181,
    "Number of People": 1,
    "Category": "Uncategorized"
  },
  {
    "Rank": 4,
    "Time Spent (seconds)": 156,
    "Number of People": 1,
    "Category": "Software Development"
  },
  {
    "Rank": 5,
    "Time Spent (seconds)": 98,
    "Number of People": 1,
    "Category": "Reference & Learning"
  }
]