[
  {
    "artist": {
      "mbid": "c2f6c57f-27ba-4c0d-b2fd-3348961e79a1",
      "#text": "Maisie Peters"
    },
    "streamable": "0",
    "image": [
      {
        "size": "small",
        "#text": "https://lastfm.freetls.fastly.net/i/u/34s/987f7d2ba21650a56e835237c6ea5e02.jpg"
      },
      {
        "size": "medium",
        "#text": "https://lastfm.freetls.fastly.net/i/u/64s/987f7d2ba21650a56e835237c6ea5e02.jpg"
      },
      {
        "size": "large",
        "#text": "https://lastfm.freetls.fastly.net/i/u/174s/987f7d2ba21650a56e835237c6ea5e02.jpg"
      },
      {
        "size": "extralarge",
        "#text": "https://lastfm.freetls.fastly.net/i/u/300x300/987f7d2ba21650a56e835237c6ea5e02.jpg"
      }
    ],
    "mbid": "",
    "album": {
      "mbid": "d0839db3-b49a-4d56-8a0b-b39dc41de8fa",
      "#text": "Trying: Season 2 (Apple TV+ Original Series Soundtrack)"
    },
    "name": "Happy Hunting Ground (feat. Griff)",
    "url": "https://www.last.fm/music/Maisie+Peters/_/Happy+Hunting+Ground+(feat.+Griff)",
    "date": {
      "uts": "1767831287",
      "#text": "08 Jan 2026, 00:14"
    }
  },
  {
    "artist": {
      "mbid": "c2f6c57f-27ba-4c0d-b2fd-3348961e79a1",
      "#text": "Maisie Peters"
    },
    "streamable": "0",
    "image": [
      {
        "size": "small",
        "#text": "https://lastfm.freetls.fastly.net/i/u/34s/987f7d2ba21650a56e835237c6ea5e02.jpg"
      },
      {
        "size": "medium",
        "#text": "https://lastfm.freetls.fastly.net/i/u/64s/987f7d2ba21650a56e835237c6ea5e02.jpg"
      },
      {
        "size": "large",
        "#text": "https://lastfm.freetls.fastly.net/i/u/174s/987f7d2ba21650a56e835237c6ea5e02.jpg"
      },
      {
        "size": "extralarge",
        "#text": "https://lastfm.freetls.fastly.net/i/u/300x300/987f7d2ba21650a56e835237c6ea5e02.jpg"
      }
    ],
    "mbid": "c6a0ca09-a58f-4bbb-a915-70f4f682a71d",
    "album": {
      "mbid": "d0839db3-b49a-4d56-8a0b-b39dc41de8fa",
      "#text": "Trying: Season 2 (Apple TV+ Original Series Soundtrack)"
    },
    "name": "Helicopter",
    "url": "https://www.last.fm/music/Maisie+Peters/_/Helicopter",
    "date": {
      "uts": "1767831054",
      "#text": "08 Jan 2026, 00:10"
    }
  },
  {
    "artist": {
      "mbid": "c2f6c57f-27ba-4c0d-b2fd-3348961e79a1",
      "#text": "Maisie Peters"
    },
    "streamable": "0",
    "image": [
      {
        "size": "small",
        "#text": "https://lastfm.freetls.fastly.net/i/u/34s/987f7d2ba21650a56e835237c6ea5e02.jpg"
      },
      {
        "size": "medium",
        "#text": "https://lastfm.freetls.fastly.net/i/u/64s/987f7d2ba21650a56e835237c6ea5e02.jpg"
      },
      {
        "size": "large",
        "#text": "https://lastfm.freetls.fastly.net/i/u/174s/987f7d2ba21650a56e835237c6ea5e02.jpg"
      },
      {
        "size": "extralarge",
        "#text": "https://lastfm.freetls.fastly.net/i/u/300x300/987f7d2ba21650a56e835237c6ea5e02.jpg"
      }
    ],
    "mbid": "",
    "album": {
      "mbid": "d0839db3-b49a-4d56-8a0b-b39dc41de8fa",
      "#text": "Trying: Season 2 (Apple TV+ Original Series Soundtrack)"
    },
    "name": "Funeral (feat. James Bay)",
    "url": "https://www.last.fm/music/Maisie+Peters/_/Funeral+(feat.+James+Bay)",
    "date": {
      "uts": "1767830758",
      "#text": "08 Jan 2026, 00:05"
    }
  },
  {
    "artist": {
      "mbid": "c2f6c57f-27ba-4c0d-b2fd-3348961e79a1",
      "#text": "Maisie Peters"
    },
    "streamable": "0",
    "image": [
      {
        "size": "small",
        "#text": "https://lastfm.freetls.fastly.net/i/u/34s/987f7d2ba21650a56e835237c6ea5e02.jpg"
      },
      {
        "size": "medium",
        "#text": "https://lastfm.freetls.fastly.net/i/u/64s/987f7d2ba21650a56e835237c6ea5e02.jpg"
      },
      {
        "size": "large",
        "#text": "https://lastfm.freetls.fastly.net/i/u/174s/987f7d2ba21650a56e835237c6ea5e02.jpg"
      },
      {
        "size": "extralarge",
        "#text": "https://lastfm.freetls.fastly.net/i/u/300x300/987f7d2ba21650a56e835237c6ea5e02.jpg"
      }
    ],
    "mbid": "a864df59-e8a1-4e8e-8323-6f36a9b82cc0",
    "album": {
      "mbid": "d0839db3-b49a-4d56-8a0b-b39dc41de8fa",
      "#text": "Trying: Season 2 (Apple TV+ Original Series Soundtrack)"
    },
    "name": "Milhouse",
    "url": "https://www.last.fm/music/Maisie+Peters/_/Milhouse",
    "date": {
      "uts": "1767830604",
      "#text": "08 Jan 2026, 00:03"
    }
  },
  {
    "artist": {
      "mbid": "c2f6c57f-27ba-4c0d-b2fd-3348961e79a1",
      "#text": "Maisie Peters"
    },
    "streamable": "0",
    "image": [
      {
        "size": "small",
        "#text": "https://lastfm.freetls.fastly.net/i/u/34s/987f7d2ba21650a56e835237c6ea5e02.jpg"
      },
      {
        "size": "medium",
        "#text": "https://lastfm.freetls.fastly.net/i/u/64s/987f7d2ba21650a56e835237c6ea5e02.jpg"
      },
      {
        "size": "large",
        "#text": "https://lastfm.freetls.fastly.net/i/u/174s/987f7d2ba21650a56e835237c6ea5e02.jpg"
      },
      {
        "size": "extralarge",
        "#text": "https://lastfm.freetls.fastly.net/i/u/300x300/987f7d2ba21650a56e835237c6ea5e02.jpg"
      }
    ],
    "mbid": "a31ddce3-5468-457b-9e0d-489e64e0264e",
    "album": {
      "mbid": "d0839db3-b49a-4d56-8a0b-b39dc41de8fa",
      "#text": "Trying: Season 2 (Apple TV+ Original Series Soundtrack)"
    },
    "name": "Neck Of The Woods",
    "url": "https://www.last.fm/music/Maisie+Peters/_/Neck+Of+The+Woods",
    "date": {
      "uts": "1767830454",
      "#text": "08 Jan 2026, 00:00"
    }
  }
]