{
  "1": {
    "steps": 280444,
    "total": 13128,
    "cal_active": 13724,
    "cal_total": 82005,
    "score": 2446
  },
  "2": {
    "steps": 242084,
    "total": 10363,
    "cal_active": 12324,
    "cal_total": 73774,
    "score": 2067
  },
  "3": {
    "steps": 260520,
    "total": 11428,
    "cal_active": 14410,
    "cal_total": 82080,
    "score": 2384
  },
  "4": {
    "steps": 233847,
    "total": 10454,
    "cal_active": 11350,
    "cal_total": 74767,
    "score": 2084
  },
  "5": {
    "steps": 281982,
    "total": 10271,
    "cal_active": 14404,
    "cal_total": 81615,
    "score": 2284
  },
  "6": {
    "steps": 167725,
    "total": 6219,
    "cal_active": 8622,
    "cal_total": 55305,
    "score": 1747
  },
  "7": {},
  "8": {},
  "9": {},
  "10": {},
  "11": {},
  "12": {}
}