{
  "1": {
    "steps": 10171,
    "total": 530,
    "cal_active": 519,
    "cal_total": 2768,
    "score": 66
  },
  "2": {
    "steps": 8138,
    "total": 334,
    "cal_active": 387,
    "cal_total": 2490,
    "score": 61
  },
  "3": {
    "steps": 9211,
    "total": 399,
    "cal_active": 415,
    "cal_total": 2649,
    "score": 61
  },
  "4": {
    "steps": 8204,
    "total": 359,
    "cal_active": 401,
    "cal_total": 2612,
    "score": 64
  },
  "5": {
    "steps": 10361,
    "total": 309,
    "cal_active": 440,
    "cal_total": 2549,
    "score": 71
  },
  "6": {
    "steps": 6065,
    "total": 358,
    "cal_active": 309,
    "cal_total": 2504,
    "score": 70
  },
  "7": {
    "steps": 4608,
    "total": 233,
    "cal_active": 231,
    "cal_total": 2379,
    "score": 77
  },
  "8": {
    "steps": 9660,
    "total": 371,
    "cal_active": 456,
    "cal_total": 2641,
    "score": 76
  },
  "9": {
    "steps": 14288,
    "total": 406,
    "cal_active": 659,
    "cal_total": 2864,
    "score": 90
  },
  "10": {
    "steps": 8751,
    "total": 418,
    "cal_active": 417,
    "cal_total": 2617,
    "score": 85
  },
  "11": {
    "steps": 7329,
    "total": 233,
    "cal_active": 320,
    "cal_total": 2413,
    "score": 79
  },
  "12": {
    "steps": 7752,
    "total": 347,
    "cal_active": 470,
    "cal_total": 2572,
    "score": 78
  },
  "13": {
    "steps": 8260,
    "total": 436,
    "cal_active": 417,
    "cal_total": 2631,
    "score": 71
  },
  "14": {
    "steps": 10501,
    "total": 458,
    "cal_active": 474,
    "cal_total": 2674,
    "score": 70
  },
  "15": {
    "steps": 9016,
    "total": 414,
    "cal_active": 515,
    "cal_total": 2701,
    "score": 75
  },
  "16": {
    "steps": 4780,
    "total": 124,
    "cal_active": 230,
    "cal_total": 2145,
    "score": 65
  },
  "17": {},
  "18": {},
  "19": {},
  "20": {},
  "21": {},
  "22": {},
  "23": {},
  "24": {},
  "25": {},
  "26": {},
  "27": {}
}