{
  "2023-07-16": {
    "score": 86,
    "score_activity_balance": 60,
    "score_hrv_balance": 91,
    "score_previous_day": 65,
    "score_previous_night": 73,
    "score_recovery_index": 60,
    "score_resting_hr": 88,
    "score_sleep_balance": 87,
    "score_temperature": 91
  },
  "2023-07-17": {
    "score": 89,
    "score_activity_balance": 79,
    "score_hrv_balance": 90,
    "score_previous_day": 90,
    "score_previous_night": 83,
    "score_recovery_index": 100,
    "score_resting_hr": 100,
    "score_sleep_balance": 95,
    "score_temperature": 96
  },
  "2023-07-18": {
    "score": 89,
    "score_activity_balance": 82,
    "score_hrv_balance": 92,
    "score_previous_day": 90,
    "score_previous_night": 75,
    "score_recovery_index": 99,
    "score_resting_hr": 100,
    "score_sleep_balance": 95,
    "score_temperature": 100
  },
  "2023-07-19": {},
  "2023-07-20": {},
  "2023-07-21": {},
  "2023-07-22": {}
}