{
  "2023-09-3": {
    "steps": 13205,
    "total": 476,
    "cal_active": 572,
    "cal_total": 2733,
    "score": 93
  },
  "2023-09-4": {
    "steps": 16016,
    "total": 575,
    "cal_active": 693,
    "cal_total": 2937,
    "score": 88
  },
  "2023-09-5": {
    "steps": 6730,
    "total": 273,
    "cal_active": 326,
    "cal_total": 2464,
    "score": 83
  },
  "2023-09-6": {
    "steps": 71,
    "total": 39,
    "cal_active": 109,
    "cal_total": 2081,
    "score": 91
  },
  "2023-09-7": {
    "steps": 12788,
    "total": 434,
    "cal_active": 603,
    "cal_total": 2774,
    "score": 86
  },
  "2023-09-8": {
    "steps": 3444,
    "total": 79,
    "cal_active": 151,
    "cal_total": 2032,
    "score": 77
  },
  "2023-09-9": {}
}