{
  "2023-09-10": {
    "steps": 8165,
    "total": 393,
    "cal_active": 388,
    "cal_total": 2522,
    "score": 81
  },
  "2023-09-11": {
    "steps": 13562,
    "total": 462,
    "cal_active": 575,
    "cal_total": 2737,
    "score": 85
  },
  "2023-09-12": {
    "steps": 9190,
    "total": 391,
    "cal_active": 429,
    "cal_total": 2572,
    "score": 84
  },
  "2023-09-13": {
    "steps": 5558,
    "total": 262,
    "cal_active": 246,
    "cal_total": 2352,
    "score": 80
  },
  "2023-09-14": {
    "steps": 6130,
    "total": 341,
    "cal_active": 270,
    "cal_total": 2462,
    "score": 71
  },
  "2023-09-15": {
    "steps": 1970,
    "total": 62,
    "cal_active": 82,
    "cal_total": 1944,
    "score": 68
  },
  "2023-09-16": {}
}