{
  "2023-10-1": {
    "steps": 16870,
    "total": 454,
    "cal_active": 742,
    "cal_total": 2905,
    "score": 79
  },
  "2023-10-2": {
    "steps": 7313,
    "total": 258,
    "cal_active": 357,
    "cal_total": 2448,
    "score": 78
  },
  "2023-10-3": {
    "steps": 5633,
    "total": 244,
    "cal_active": 280,
    "cal_total": 2484,
    "score": 72
  },
  "2023-10-4": {
    "steps": 8464,
    "total": 284,
    "cal_active": 397,
    "cal_total": 2499,
    "score": 80
  },
  "2023-10-5": {
    "steps": 2498,
    "total": 87,
    "cal_active": 121,
    "cal_total": 2015,
    "score": 73
  },
  "2023-10-6": {},
  "2023-10-7": {}
}