{
  "1": {
    "total": 710040,
    "rem": 88590,
    "awake": 119220,
    "deep": 238530,
    "duration": 829260,
    "efficiency": 2396,
    "light": 382920,
    "score": 1923
  },
  "2": {
    "total": 710040,
    "rem": 83640,
    "awake": 107400,
    "deep": 248550,
    "duration": 817440,
    "efficiency": 2344,
    "light": 377850,
    "score": 2015
  },
  "3": {
    "total": 800520,
    "rem": 99600,
    "awake": 145920,
    "deep": 280890,
    "duration": 946440,
    "efficiency": 2543,
    "light": 420030,
    "score": 2242
  },
  "4": {
    "total": 30060,
    "rem": 3300,
    "awake": 4680,
    "deep": 9000,
    "duration": 34740,
    "efficiency": 87,
    "light": 17760,
    "score": 81
  },
  "5": {},
  "6": {},
  "7": {},
  "8": {},
  "9": {},
  "10": {},
  "11": {},
  "12": {}
}