{
  "2023-10-8": {
    "total": 29340,
    "rem": 3750,
    "awake": 3900,
    "deep": 10740,
    "duration": 33240,
    "efficiency": 88,
    "light": 14850,
    "score": 77
  },
  "2023-10-9": {
    "total": 27060,
    "rem": 4410,
    "awake": 5580,
    "deep": 8460,
    "duration": 32640,
    "efficiency": 83,
    "light": 14190,
    "score": 75
  },
  "2023-10-10": {
    "total": 30600,
    "rem": 3240,
    "awake": 4500,
    "deep": 10770,
    "duration": 35100,
    "efficiency": 87,
    "light": 16590,
    "score": 75
  },
  "2023-10-11": {},
  "2023-10-12": {
    "total": 31230,
    "rem": 2880,
    "awake": 4170,
    "deep": 10710,
    "duration": 35400,
    "efficiency": 88,
    "light": 17640,
    "score": 76
  },
  "2023-10-13": {},
  "2023-10-14": {}
}