[
  {
    "summary_date": "2023-09-24",
    "period_id": 1,
    "is_longest": 1,
    "timezone": -420,
    "bedtime_end": "2023-09-25T07:01:31-07:00",
    "bedtime_start": "2023-09-24T23:30:31-07:00",
    "type": "long_sleep",
    "breath_average": 13.25,
    "average_breath_variation": 3.625,
    "duration": 27060,
    "total": 23250,
    "awake": 3810,
    "rem": 2280,
    "deep": 6870,
    "light": 14100,
    "midpoint_time": 14550,
    "efficiency": 86,
    "restless": 6,
    "onset_latency": 540,
    "got_up_count": 0,
    "wake_up_count": 8,
    "hr_5min": [
      0,
      0,
      0,
      0,
      70,
      66,
      65,
      59,
      0,
      57,
      60,
      60,
      62,
      0,
      63,
      0,
      58,
      57,
      57,
      60,
      71,
      68,
      64,
      59,
      62,
      59,
      59,
      59,
      61,
      64,
      0,
      0,
      59,
      59,
      60,
      57,
      58,
      56,
      59,
      61,
      65,
      62,
      62,
      62,
      62,
      56,
      58,
      60,
      59,
      62,
      64,
      66,
      64,
      62,
      58,
      64,
      63,
      61,
      65,
      59,
      59,
      61,
      63,
      62,
      63,
      56,
      59,
      60,
      61,
      60,
      62,
      63,
      67,
      69,
      69,
      73,
      58,
      71,
      67,
      66,
      54,
      58,
      58,
      56,
      59,
      60,
      63,
      59,
      58,
      56,
      61
    ],
    "hr_average": 61.39,
    "hr_lowest": 54,
    "lowest_heart_rate_time_offset": 13770,
    "hypnogram_5min": "4224444442211112242233242211111122212222322222221111122233222222222222211111233222222112224",
    "rmssd": 121,
    "rmssd_5min": [
      0,
      0,
      0,
      0,
      95,
      120,
      127,
      163,
      0,
      134,
      126,
      127,
      134,
      0,
      120,
      0,
      110,
      107,
      127,
      112,
      91,
      96,
      110,
      114,
      130,
      133,
      124,
      130,
      142,
      79,
      0,
      0,
      106,
      131,
      132,
      130,
      134,
      126,
      116,
      112,
      87,
      130,
      125,
      115,
      122,
      152,
      151,
      146,
      160,
      127,
      123,
      122,
      111,
      98,
      166,
      114,
      91,
      123,
      91,
      158,
      147,
      132,
      105,
      110,
      117,
      157,
      159,
      158,
      121,
      138,
      110,
      106,
      92,
      90,
      84,
      79,
      135,
      57,
      98,
      96,
      140,
      123,
      137,
      163,
      160,
      158,
      119,
      114,
      141,
      157,
      122
    ],
    "score": 70,
    "score_alignment": 83,
    "score_deep": 97,
    "score_disturbances": 67,
    "score_efficiency": 86,
    "score_latency": 83,
    "score_rem": 30,
    "score_total": 64,
    "temperature_deviation": 0.3,
    "temperature_trend_deviation": 0.39,
    "bedtime_start_delta": -1769,
    "bedtime_end_delta": 25291,
    "midpoint_at_delta": 12781,
    "temperature_delta": 0.3
  }
]