{
  "2020": {
    "total": 2833350,
    "rem": 338250,
    "awake": 567090,
    "deep": 912030,
    "duration": 3400440,
    "efficiency": 8920,
    "light": 1583070,
    "score": 7162
  },
  "2021": {
    "total": 6511560,
    "rem": 731340,
    "awake": 1267560,
    "deep": 2203740,
    "duration": 7779120,
    "efficiency": 20973,
    "light": 3576480,
    "score": 17351
  },
  "2022": {
    "total": 4764030,
    "rem": 576510,
    "awake": 837750,
    "deep": 1506360,
    "duration": 5601780,
    "efficiency": 15089,
    "light": 2681160,
    "score": 12884
  }
}